[
    {
        "id": "110050235795384512",
        "username": "feedle",
        "acct": "feedle",
        "display_name": "feedle",
        "locked": false,
        "bot": false,
        "discoverable": true,
        "indexable": false,
        "group": false,
        "created_at": "2023-03-19T00:00:00.000Z",
        "note": "<p>feedle is a search engine for blogs and podcasts, where every search has its own RSS feed.</p><p>Subscribe and stay up-to-date when a new result matches your criteria.</p><p>Discover content creators you may not know about, all from a single RSS feed, solely based on your interests.</p>",
        "url": "https://mastodon.social/@feedle",
        "uri": "https://mastodon.social/users/feedle",
        "avatar": "https://files.mastodon.social/accounts/avatars/110/050/235/795/384/512/original/53bfd4dcf651bb24.jpeg",
        "avatar_static": "https://files.mastodon.social/accounts/avatars/110/050/235/795/384/512/original/53bfd4dcf651bb24.jpeg",
        "header": "https://files.mastodon.social/accounts/headers/110/050/235/795/384/512/original/4c4eacd89eaa5f66.jpeg",
        "header_static": "https://files.mastodon.social/accounts/headers/110/050/235/795/384/512/original/4c4eacd89eaa5f66.jpeg",
        "followers_count": 728,
        "following_count": 153,
        "statuses_count": 782,
        "last_status_at": "2024-08-30",
        "hide_collections": false,
        "noindex": false,
        "emojis": [],
        "roles": [],
        "fields": [
            {
                "name": "Feedle",
                "value": "<a href=\"https://feedle.world\" target=\"_blank\" rel=\"nofollow noopener noreferrer me\" translate=\"no\"><span class=\"invisible\">https://</span><span class=\"\">feedle.world</span><span class=\"invisible\"></span></a>",
                "verified_at": "2024-01-24T15:54:36.022+00:00"
            },
            {
                "name": "Submit your blog or podcast",
                "value": "<a href=\"https://tally.so/r/mJ11E7\" target=\"_blank\" rel=\"nofollow noopener noreferrer me\" translate=\"no\"><span class=\"invisible\">https://</span><span class=\"\">tally.so/r/mJ11E7</span><span class=\"invisible\"></span></a>",
                "verified_at": null
            },
            {
                "name": "Chief Feedlers",
                "value": "<span class=\"h-card\" translate=\"no\"><a href=\"https://mastodon.social/@preslavrachev\" class=\"u-url mention\">@<span>preslavrachev</span></a></span> and <span class=\"h-card\" translate=\"no\"><a href=\"https://mastodon.in-two.com/@gi\" class=\"u-url mention\">@<span>gi@in-two.com</span></a></span>",
                "verified_at": null
            }
        ]
    },
    {
        "id": "111622330085307004",
        "username": "GurdeepPandher",
        "acct": "GurdeepPandher",
        "display_name": "Gurdeep Pandher of the Yukon",
        "locked": false,
        "bot": false,
        "discoverable": null,
        "indexable": false,
        "group": false,
        "created_at": "2023-12-22T00:00:00.000Z",
        "note": "<p>Adding joy, hope and togetherness to the world grappled with sadness, stress, and divisions.</p>",
        "url": "https://mastodon.social/@GurdeepPandher",
        "uri": "https://mastodon.social/users/GurdeepPandher",
        "avatar": "https://files.mastodon.social/accounts/avatars/111/622/330/085/307/004/original/43e8e6d3faac1b1c.png",
        "avatar_static": "https://files.mastodon.social/accounts/avatars/111/622/330/085/307/004/original/43e8e6d3faac1b1c.png",
        "header": "https://files.mastodon.social/accounts/headers/111/622/330/085/307/004/original/b55fcfb4b80da4c0.png",
        "header_static": "https://files.mastodon.social/accounts/headers/111/622/330/085/307/004/original/b55fcfb4b80da4c0.png",
        "followers_count": 11599,
        "following_count": 0,
        "statuses_count": 108,
        "last_status_at": "2024-08-29",
        "hide_collections": null,
        "noindex": false,
        "emojis": [],
        "roles": [],
        "fields": []
    },
    {
        "id": "144504",
        "username": "Neuromancer",
        "acct": "Neuromancer",
        "display_name": "kall\u00f3d\u00f3 egzisztencia, Esq.",
        "locked": false,
        "bot": false,
        "discoverable": true,
        "indexable": false,
        "group": false,
        "created_at": "2017-05-21T00:00:00.000Z",
        "note": "<p>a n\u00e9hai Els\u0151 Nemzeti (Mastodon) Instancia \u00fczemeltet\u0151je.</p>",
        "url": "https://mastodon.social/@Neuromancer",
        "uri": "https://mastodon.social/users/Neuromancer",
        "avatar": "https://files.mastodon.social/accounts/avatars/000/144/504/original/171285670495a8d0.jpg",
        "avatar_static": "https://files.mastodon.social/accounts/avatars/000/144/504/original/171285670495a8d0.jpg",
        "header": "https://files.mastodon.social/accounts/headers/000/144/504/original/edeb2ee37f374b64.jpg",
        "header_static": "https://files.mastodon.social/accounts/headers/000/144/504/original/edeb2ee37f374b64.jpg",
        "followers_count": 113,
        "following_count": 28,
        "statuses_count": 211,
        "last_status_at": "2024-08-11",
        "hide_collections": null,
        "noindex": false,
        "emojis": [],
        "roles": [],
        "fields": []
    },
    {
        "id": "110648362462136941",
        "username": "agatity",
        "acct": "agatity",
        "display_name": "",
        "locked": false,
        "bot": false,
        "discoverable": true,
        "indexable": false,
        "group": false,
        "created_at": "2023-07-03T00:00:00.000Z",
        "note": "",
        "url": "https://mastodon.social/@agatity",
        "uri": "https://mastodon.social/users/agatity",
        "avatar": "https://files.mastodon.social/accounts/avatars/110/648/362/462/136/941/original/1756fb71f977aeb8.png",
        "avatar_static": "https://files.mastodon.social/accounts/avatars/110/648/362/462/136/941/original/1756fb71f977aeb8.png",
        "header": "https://mastodon.social/headers/original/missing.png",
        "header_static": "https://mastodon.social/headers/original/missing.png",
        "followers_count": 1,
        "following_count": 2,
        "statuses_count": 0,
        "last_status_at": null,
        "hide_collections": true,
        "noindex": false,
        "emojis": [],
        "roles": [],
        "fields": []
    },
    {
        "id": "109392565556599908",
        "username": "AaronSwartzDay",
        "acct": "AaronSwartzDay",
        "display_name": "AaronSwartzDay",
        "locked": false,
        "bot": false,
        "discoverable": false,
        "indexable": false,
        "group": false,
        "created_at": "2022-11-23T00:00:00.000Z",
        "note": "<p>We put on The Aaron Swartz Day and International Hackathon every year, and our Co-founder, Lisa Rein, worked with Aaron founding Creative Commons. 2023 will be the 10 year anniversary of Aaron&#39;s death and we will be working on projects all year in his memory. aaronswartzday.org</p>",
        "url": "https://mastodon.social/@AaronSwartzDay",
        "uri": "https://mastodon.social/users/AaronSwartzDay",
        "avatar": "https://files.mastodon.social/accounts/avatars/109/392/565/556/599/908/original/a3dbe6b02859a3cd.jpg",
        "avatar_static": "https://files.mastodon.social/accounts/avatars/109/392/565/556/599/908/original/a3dbe6b02859a3cd.jpg",
        "header": "https://mastodon.social/headers/original/missing.png",
        "header_static": "https://mastodon.social/headers/original/missing.png",
        "followers_count": 143,
        "following_count": 26,
        "statuses_count": 47,
        "last_status_at": "2023-11-11",
        "hide_collections": false,
        "noindex": false,
        "emojis": [],
        "roles": [],
        "fields": []
    },
    {
        "id": "109252185616938267",
        "username": "lizupton",
        "acct": "lizupton",
        "display_name": "Liz Upton",
        "locked": false,
        "bot": false,
        "discoverable": true,
        "indexable": false,
        "group": false,
        "created_at": "2022-10-29T00:00:00.000Z",
        "note": "<p>Raspberry Pi, paint, abstruse ferments in jars.</p>",
        "url": "https://mastodon.social/@lizupton",
        "uri": "https://mastodon.social/users/lizupton",
        "avatar": "https://files.mastodon.social/accounts/avatars/109/252/185/616/938/267/original/228ff6cb84dc7421.jpeg",
        "avatar_static": "https://files.mastodon.social/accounts/avatars/109/252/185/616/938/267/original/228ff6cb84dc7421.jpeg",
        "header": "https://mastodon.social/headers/original/missing.png",
        "header_static": "https://mastodon.social/headers/original/missing.png",
        "followers_count": 1297,
        "following_count": 34,
        "statuses_count": 56,
        "last_status_at": "2023-03-31",
        "hide_collections": false,
        "noindex": false,
        "emojis": [],
        "roles": [],
        "fields": []
    },
    {
        "id": "772454",
        "username": "Decentralize_today",
        "acct": "Decentralize_today",
        "display_name": "Decentralize.Today",
        "locked": false,
        "bot": false,
        "discoverable": true,
        "indexable": false,
        "group": false,
        "created_at": "2019-03-23T00:00:00.000Z",
        "note": "<p>We operate privacy.do and decentralize.today. No Ads, no trackers! <a href=\"https://mastodon.social/tags/privacymatters\" class=\"mention hashtag\" rel=\"tag\">#<span>privacymatters</span></a></p><p>You can make your contribution to the following Monero (xmr) address:</p><p>87oFTJTwSMZSnvDA6Gct2LLHWf9C1io1aFY4kJoamuhzH973Z16JkD63ntypgibbUYDDtZYcydSY84RNthfF6bUp81zPjv6</p>",
        "url": "https://mastodon.social/@Decentralize_today",
        "uri": "https://mastodon.social/users/Decentralize_today",
        "avatar": "https://files.mastodon.social/accounts/avatars/000/772/454/original/222cf8135cf9c35a.png",
        "avatar_static": "https://files.mastodon.social/accounts/avatars/000/772/454/original/222cf8135cf9c35a.png",
        "header": "https://files.mastodon.social/accounts/headers/000/772/454/original/1194Decentralize.Today-Logo-Tagline-V3-01-DarkBG.png",
        "header_static": "https://files.mastodon.social/accounts/headers/000/772/454/original/1194Decentralize.Today-Logo-Tagline-V3-01-DarkBG.png",
        "followers_count": 466,
        "following_count": 166,
        "statuses_count": 6370,
        "last_status_at": "2023-05-01",
        "hide_collections": false,
        "noindex": false,
        "moved": {
            "id": "110293023998753569",
            "username": "Decentralize",
            "acct": "Decentralize@dt.gl",
            "display_name": "The Privacy Advocate (dt.gl)",
            "locked": false,
            "bot": false,
            "discoverable": true,
            "indexable": true,
            "group": false,
            "created_at": "2023-05-01T00:00:00.000Z",
            "note": "<p>Your Daily Dose of Decentralization</p>",
            "url": "https://dt.gl/@Decentralize",
            "uri": "https://dt.gl/users/Decentralize",
            "avatar": "https://files.mastodon.social/cache/accounts/avatars/110/293/023/998/753/569/original/61407cbb81b0c228.jpeg",
            "avatar_static": "https://files.mastodon.social/cache/accounts/avatars/110/293/023/998/753/569/original/61407cbb81b0c228.jpeg",
            "header": "https://files.mastodon.social/cache/accounts/headers/110/293/023/998/753/569/original/f56af10868c7d1b7.jpeg",
            "header_static": "https://files.mastodon.social/cache/accounts/headers/110/293/023/998/753/569/original/f56af10868c7d1b7.jpeg",
            "followers_count": 2354,
            "following_count": 185,
            "statuses_count": 3063,
            "last_status_at": "2024-08-29",
            "hide_collections": false,
            "emojis": [],
            "fields": [
                {
                    "name": "BTC",
                    "value": "bc1qnw4qgw6mh00txpt7k6ze479q9wqsd4agpkgyj4",
                    "verified_at": null
                },
                {
                    "name": "XMR Monero",
                    "value": "87oFTJTwSMZSnvDA6Gct2LLHWf9C1io1aFY4kJoamuhzH973Z16JkD63ntypgibbUYDDtZYcydSY84RNthfF6bUp81zPjv6",
                    "verified_at": null
                },
                {
                    "name": "Firo",
                    "value": "a5udxK6rbr59qw1nLsiBQTuzUkWBjVReHr",
                    "verified_at": null
                }
            ]
        },
        "emojis": [],
        "roles": [],
        "fields": [
            {
                "name": "www",
                "value": "<a href=\"https://decentralize.today\" target=\"_blank\" rel=\"nofollow noopener noreferrer me\" translate=\"no\"><span class=\"invisible\">https://</span><span class=\"\">decentralize.today</span><span class=\"invisible\"></span></a>",
                "verified_at": null
            },
            {
                "name": "www",
                "value": "<a href=\"https://privacy.do\" target=\"_blank\" rel=\"nofollow noopener noreferrer me\" translate=\"no\"><span class=\"invisible\">https://</span><span class=\"\">privacy.do</span><span class=\"invisible\"></span></a>",
                "verified_at": "2022-05-10T01:59:05.209+00:00"
            },
            {
                "name": "Support Us",
                "value": "<a href=\"https://privacy.do/donate\" target=\"_blank\" rel=\"nofollow noopener noreferrer me\" translate=\"no\"><span class=\"invisible\">https://</span><span class=\"\">privacy.do/donate</span><span class=\"invisible\"></span></a>",
                "verified_at": "2022-05-10T01:59:05.491+00:00"
            },
            {
                "name": "Lemmy",
                "value": "<a href=\"https://lemmy.ml/c/privacydo\" target=\"_blank\" rel=\"nofollow noopener noreferrer me\" translate=\"no\"><span class=\"invisible\">https://</span><span class=\"\">lemmy.ml/c/privacydo</span><span class=\"invisible\"></span></a>",
                "verified_at": null
            }
        ]
    },
    {
        "id": "199851",
        "username": "itsfoss",
        "acct": "itsfoss",
        "display_name": "It's FOSS",
        "locked": false,
        "bot": false,
        "discoverable": true,
        "indexable": false,
        "group": false,
        "created_at": "2017-09-12T00:00:00.000Z",
        "note": "<p>World&#39;s leading Linux and Open Source web portal.<br /><a href=\"https://itsfoss.com/\" target=\"_blank\" rel=\"nofollow noopener noreferrer\" translate=\"no\"><span class=\"invisible\">https://</span><span class=\"\">itsfoss.com/</span><span class=\"invisible\"></span></a></p>",
        "url": "https://mastodon.social/@itsfoss",
        "uri": "https://mastodon.social/users/itsfoss",
        "avatar": "https://files.mastodon.social/accounts/avatars/000/199/851/original/21292f83459dd19d.png",
        "avatar_static": "https://files.mastodon.social/accounts/avatars/000/199/851/original/21292f83459dd19d.png",
        "header": "https://files.mastodon.social/accounts/headers/000/199/851/original/e12294e385e0a771.png",
        "header_static": "https://files.mastodon.social/accounts/headers/000/199/851/original/e12294e385e0a771.png",
        "followers_count": 16460,
        "following_count": 25,
        "statuses_count": 4507,
        "last_status_at": "2024-08-30",
        "hide_collections": false,
        "noindex": false,
        "emojis": [],
        "roles": [],
        "fields": [
            {
                "name": "Website",
                "value": "<a href=\"https://itsfoss.com/\" target=\"_blank\" rel=\"nofollow noopener noreferrer me\" translate=\"no\"><span class=\"invisible\">https://</span><span class=\"\">itsfoss.com/</span><span class=\"invisible\"></span></a>",
                "verified_at": "2022-11-17T06:33:14.494+00:00"
            }
        ]
    },
    {
        "id": "377402",
        "username": "fsfe",
        "acct": "fsfe",
        "display_name": "Free Software Foundation Europe",
        "locked": false,
        "bot": false,
        "discoverable": true,
        "indexable": false,
        "group": false,
        "created_at": "2018-06-21T00:00:00.000Z",
        "note": "<p>:fsfe: Free Software Foundation Europe is a charity that empowers users to control technology. Software is deeply involved in all aspects of our lives. <a href=\"https://mastodon.social/tags/FreeSoftware\" class=\"mention hashtag\" rel=\"tag\">#<span>FreeSoftware</span></a> (aka <a href=\"https://mastodon.social/tags/OpenSource\" class=\"mention hashtag\" rel=\"tag\">#<span>OpenSource</span></a>) gives everybody the rights to use, understand, adapt, and share software. These rights help support other fundamental rights like freedom of speech, freedom of press, and privacy. <a href=\"https://mastodon.social/tags/SoftwareFreedom\" class=\"mention hashtag\" rel=\"tag\">#<span>SoftwareFreedom</span></a> </p><p>Public Money? <a href=\"https://mastodon.social/tags/PublicCode\" class=\"mention hashtag\" rel=\"tag\">#<span>PublicCode</span></a> ! <a href=\"https://mastodon.social/tags/DeviceNeutrality\" class=\"mention hashtag\" rel=\"tag\">#<span>DeviceNeutrality</span></a> <a href=\"https://mastodon.social/tags/UpcyclingAndroid\" class=\"mention hashtag\" rel=\"tag\">#<span>UpcyclingAndroid</span></a> <a href=\"https://mastodon.social/tags/RouterFreedom\" class=\"mention hashtag\" rel=\"tag\">#<span>RouterFreedom</span></a> <a href=\"https://mastodon.social/tags/ilovefs\" class=\"mention hashtag\" rel=\"tag\">#<span>ilovefs</span></a> <a href=\"https://mastodon.social/tags/YH4F\" class=\"mention hashtag\" rel=\"tag\">#<span>YH4F</span></a> <a href=\"https://mastodon.social/tags/REUSE\" class=\"mention hashtag\" rel=\"tag\">#<span>REUSE</span></a> <a href=\"https://mastodon.social/tags/DigitalRights\" class=\"mention hashtag\" rel=\"tag\">#<span>DigitalRights</span></a></p>",
        "url": "https://mastodon.social/@fsfe",
        "uri": "https://mastodon.social/users/fsfe",
        "avatar": "https://files.mastodon.social/accounts/avatars/000/377/402/original/19edbd43c05a3fcc.png",
        "avatar_static": "https://files.mastodon.social/accounts/avatars/000/377/402/original/19edbd43c05a3fcc.png",
        "header": "https://files.mastodon.social/accounts/headers/000/377/402/original/405ce65e69621520.jpg",
        "header_static": "https://files.mastodon.social/accounts/headers/000/377/402/original/405ce65e69621520.jpg",
        "followers_count": 15823,
        "following_count": 25,
        "statuses_count": 2183,
        "last_status_at": "2024-08-30",
        "hide_collections": false,
        "noindex": false,
        "emojis": [
            {
                "shortcode": "fsfe",
                "url": "https://files.mastodon.social/custom_emojis/images/000/266/015/original/40cafccf23c39c18.png",
                "static_url": "https://files.mastodon.social/custom_emojis/images/000/266/015/static/40cafccf23c39c18.png",
                "visible_in_picker": true
            }
        ],
        "roles": [],
        "fields": [
            {
                "name": "Website",
                "value": "<a href=\"https://fsfe.org\" target=\"_blank\" rel=\"nofollow noopener noreferrer me\" translate=\"no\"><span class=\"invisible\">https://</span><span class=\"\">fsfe.org</span><span class=\"invisible\"></span></a>",
                "verified_at": "2018-09-20T21:04:02.881+00:00"
            },
            {
                "name": "Join us",
                "value": "<a href=\"https://fsfe.org/contribute/contribute\" target=\"_blank\" rel=\"nofollow noopener noreferrer me\" translate=\"no\"><span class=\"invisible\">https://</span><span class=\"\">fsfe.org/contribute/contribute</span><span class=\"invisible\"></span></a>",
                "verified_at": null
            },
            {
                "name": "Support us",
                "value": "<a href=\"https://my.fsfe.org/support\" target=\"_blank\" rel=\"nofollow noopener noreferrer me\" translate=\"no\"><span class=\"invisible\">https://</span><span class=\"\">my.fsfe.org/support</span><span class=\"invisible\"></span></a>",
                "verified_at": null
            },
            {
                "name": "PeerTube",
                "value": "<a href=\"https://media.fsfe.org\" target=\"_blank\" rel=\"nofollow noopener noreferrer me\" translate=\"no\"><span class=\"invisible\">https://</span><span class=\"\">media.fsfe.org</span><span class=\"invisible\"></span></a>",
                "verified_at": null
            }
        ]
    },
    {
        "id": "106092554110247292",
        "username": "opensourceseeds",
        "acct": "opensourceseeds",
        "display_name": "OpenSourceSeeds",
        "locked": false,
        "bot": false,
        "discoverable": true,
        "indexable": false,
        "group": false,
        "created_at": "2021-04-19T00:00:00.000Z",
        "note": "<p>OpenSourceSeeds will Saatgut wieder zu einem Gemeingut f\u00fcr Alle machen. Dazu statten wir neue Sorten mit der Open-Source Lizenz aus. Das ist ein einfacher Weg, Saatgut rechtlich vor Patenten und anderen Formen der Privatisierung zu sch\u00fctzen. </p><p>ENG: OpenSourceSeeds is committed to re-establishing seed as a common good for all. We do this by providing new varieties with an open-source licence. This is an easy way to legally protect seed from patents and other forms of privatization.</p>",
        "url": "https://mastodon.social/@opensourceseeds",
        "uri": "https://mastodon.social/users/opensourceseeds",
        "avatar": "https://files.mastodon.social/accounts/avatars/106/092/554/110/247/292/original/e34f5ecca9835bee.jpg",
        "avatar_static": "https://files.mastodon.social/accounts/avatars/106/092/554/110/247/292/original/e34f5ecca9835bee.jpg",
        "header": "https://files.mastodon.social/accounts/headers/106/092/554/110/247/292/original/cd569f41ae302099.png",
        "header_static": "https://files.mastodon.social/accounts/headers/106/092/554/110/247/292/original/cd569f41ae302099.png",
        "followers_count": 2880,
        "following_count": 42,
        "statuses_count": 447,
        "last_status_at": "2023-12-18",
        "hide_collections": false,
        "noindex": false,
        "emojis": [],
        "roles": [],
        "fields": [
            {
                "name": "Website",
                "value": "<a href=\"https://opensourceseeds.org/en\" target=\"_blank\" rel=\"nofollow noopener noreferrer me\" translate=\"no\"><span class=\"invisible\">https://</span><span class=\"\">opensourceseeds.org/en</span><span class=\"invisible\"></span></a>",
                "verified_at": null
            },
            {
                "name": "Links",
                "value": "<a href=\"https://linktr.ee/OpenSourceSeeds\" target=\"_blank\" rel=\"nofollow noopener noreferrer me\" translate=\"no\"><span class=\"invisible\">https://</span><span class=\"\">linktr.ee/OpenSourceSeeds</span><span class=\"invisible\"></span></a>",
                "verified_at": null
            }
        ]
    },
    {
        "id": "594698",
        "username": "kiwix",
        "acct": "kiwix",
        "display_name": "Kiwix",
        "locked": false,
        "bot": false,
        "discoverable": true,
        "indexable": false,
        "group": false,
        "created_at": "2018-11-24T00:00:00.000Z",
        "note": "<p>Web content for people without internet access. Go <a href=\"https://mastodon.social/tags/offline\" class=\"mention hashtag\" rel=\"tag\">#<span>offline</span></a> and take Wikipedia, TED talks, the Gutenberg Project library &amp; more with you! <a href=\"https://kiwix.org\" target=\"_blank\" rel=\"nofollow noopener noreferrer\" translate=\"no\"><span class=\"invisible\">https://</span><span class=\"\">kiwix.org</span><span class=\"invisible\"></span></a></p>",
        "url": "https://mastodon.social/@kiwix",
        "uri": "https://mastodon.social/users/kiwix",
        "avatar": "https://files.mastodon.social/accounts/avatars/000/594/698/original/925938dddae95bef.jpg",
        "avatar_static": "https://files.mastodon.social/accounts/avatars/000/594/698/original/925938dddae95bef.jpg",
        "header": "https://files.mastodon.social/accounts/headers/000/594/698/original/f919b2e7017416ca.jpeg",
        "header_static": "https://files.mastodon.social/accounts/headers/000/594/698/original/f919b2e7017416ca.jpeg",
        "followers_count": 2859,
        "following_count": 577,
        "statuses_count": 2715,
        "last_status_at": "2024-08-29",
        "hide_collections": false,
        "noindex": false,
        "emojis": [],
        "roles": [],
        "fields": [
            {
                "name": "Web",
                "value": "<a href=\"https://kiwix.org\" target=\"_blank\" rel=\"nofollow noopener noreferrer me\" translate=\"no\"><span class=\"invisible\">https://</span><span class=\"\">kiwix.org</span><span class=\"invisible\"></span></a>",
                "verified_at": null
            }
        ]
    }
]