{
    "ancestors": [],
    "descendants": [
        {
            "id": "112845995395896054",
            "created_at": "2024-07-25T07:40:37.000Z",
            "in_reply_to_id": "112844971691041983",
            "in_reply_to_account_id": "109504351558879098",
            "sensitive": false,
            "spoiler_text": "",
            "visibility": "public",
            "language": "en",
            "uri": "https://toot.lv/users/peteriskrisjanis/statuses/112845995186784120",
            "url": "https://toot.lv/@peteriskrisjanis/112845995186784120",
            "replies_count": 0,
            "reblogs_count": 0,
            "favourites_count": 0,
            "edited_at": null,
            "content": "<p><span class=\"h-card\" translate=\"no\"><a href=\"https://cosocial.ca/@timbray\" class=\"u-url mention\" rel=\"nofollow noopener noreferrer\" target=\"_blank\">@<span>timbray</span></a></span> but ma oil!</p>",
            "reblog": null,
            "account": {
                "id": "109307893837695279",
                "username": "peteriskrisjanis",
                "acct": "peteriskrisjanis@toot.lv",
                "display_name": "P\u0113teris Kri\u0161j\u0101nis",
                "locked": false,
                "bot": false,
                "discoverable": true,
                "indexable": false,
                "group": false,
                "created_at": "2022-11-08T00:00:00.000Z",
                "note": "<p>Balamute, m\u016bzi\u0137is, p\u0101r\u0101k j\u016bt\u012bgs cilv\u0113ks - Chatterbox, musician by heart, programming / devops / design at Frontier Developments</p>",
                "url": "https://toot.lv/@peteriskrisjanis",
                "uri": "https://toot.lv/users/peteriskrisjanis",
                "avatar": "https://files.mastodon.social/cache/accounts/avatars/109/307/893/837/695/279/original/58a98b32a0c98a96.png",
                "avatar_static": "https://files.mastodon.social/cache/accounts/avatars/109/307/893/837/695/279/original/58a98b32a0c98a96.png",
                "header": "https://files.mastodon.social/cache/accounts/headers/109/307/893/837/695/279/original/2afce5a02a938071.png",
                "header_static": "https://files.mastodon.social/cache/accounts/headers/109/307/893/837/695/279/original/2afce5a02a938071.png",
                "followers_count": 628,
                "following_count": 799,
                "statuses_count": 21960,
                "last_status_at": "2024-08-27",
                "hide_collections": false,
                "emojis": [],
                "fields": []
            },
            "media_attachments": [],
            "mentions": [
                {
                    "id": "109504351558879098",
                    "username": "timbray",
                    "url": "https://cosocial.ca/@timbray",
                    "acct": "timbray@cosocial.ca"
                }
            ],
            "tags": [],
            "emojis": [],
            "card": null,
            "poll": null
        },
        {
            "id": "112846160109409247",
            "created_at": "2024-07-25T08:22:33.629Z",
            "in_reply_to_id": "112844971691041983",
            "in_reply_to_account_id": "109504351558879098",
            "sensitive": false,
            "spoiler_text": "",
            "visibility": "public",
            "language": "en",
            "uri": "https://mastodon.social/users/Deixis9/statuses/112846160109409247",
            "url": "https://mastodon.social/@Deixis9/112846160109409247",
            "replies_count": 0,
            "reblogs_count": 12,
            "favourites_count": 22,
            "edited_at": null,
            "content": "<p><span class=\"h-card\" translate=\"no\"><a href=\"https://cosocial.ca/@timbray\" class=\"u-url mention\">@<span>timbray</span></a></span> We have been at the tipping point of +1\u2103 for 12 consecutive months.</p><p>Sunday was the hottest day ever recorded.</p><p>Then Monday was the hottest day ever recorded.</p><p>These are the consequences of climate change.</p><p>Stop voting for oil men.</p><p><a href=\"https://mastodon.social/tags/juststopoil\" class=\"mention hashtag\" rel=\"tag\">#<span>juststopoil</span></a></p>",
            "reblog": null,
            "application": {
                "name": "Web",
                "website": null
            },
            "account": {
                "id": "110156409316890091",
                "username": "Deixis9",
                "acct": "Deixis9",
                "display_name": "Trump Chaos Fatigue",
                "locked": false,
                "bot": false,
                "discoverable": false,
                "indexable": false,
                "group": false,
                "created_at": "2023-04-07T00:00:00.000Z",
                "note": "<p>Not a Sociopath!!!</p><p>Consciousness High , Neurotism Low,</p><p>This n&#39; That</p>",
                "url": "https://mastodon.social/@Deixis9",
                "uri": "https://mastodon.social/users/Deixis9",
                "avatar": "https://files.mastodon.social/accounts/avatars/110/156/409/316/890/091/original/119defa14e3210a5.png",
                "avatar_static": "https://files.mastodon.social/accounts/avatars/110/156/409/316/890/091/original/119defa14e3210a5.png",
                "header": "https://files.mastodon.social/accounts/headers/110/156/409/316/890/091/original/a36fc23e4747ee74.png",
                "header_static": "https://files.mastodon.social/accounts/headers/110/156/409/316/890/091/original/a36fc23e4747ee74.png",
                "followers_count": 112,
                "following_count": 514,
                "statuses_count": 1164,
                "last_status_at": "2024-08-27",
                "hide_collections": false,
                "noindex": false,
                "emojis": [],
                "roles": [],
                "fields": []
            },
            "media_attachments": [
                {
                    "id": "112846159728360683",
                    "type": "image",
                    "url": "https://files.mastodon.social/media_attachments/files/112/846/159/728/360/683/original/ce41b16ab98df086.png",
                    "preview_url": "https://files.mastodon.social/media_attachments/files/112/846/159/728/360/683/small/ce41b16ab98df086.png",
                    "remote_url": null,
                    "preview_remote_url": null,
                    "text_url": null,
                    "meta": {
                        "original": {
                            "width": 1046,
                            "height": 1056,
                            "size": "1046x1056",
                            "aspect": 0.990530303030303
                        },
                        "small": {
                            "width": 477,
                            "height": 482,
                            "size": "477x482",
                            "aspect": 0.9896265560165975
                        }
                    },
                    "description": null,
                    "blurhash": "UB9jcYs:0LIV#*t79aIospt6E1NG%gj[soaf"
                }
            ],
            "mentions": [
                {
                    "id": "109504351558879098",
                    "username": "timbray",
                    "url": "https://cosocial.ca/@timbray",
                    "acct": "timbray@cosocial.ca"
                }
            ],
            "tags": [
                {
                    "name": "JustStopOil",
                    "url": "https://mastodon.social/tags/JustStopOil"
                }
            ],
            "emojis": [],
            "card": null,
            "poll": null
        },
        {
            "id": "112846673845523331",
            "created_at": "2024-07-25T10:33:09.000Z",
            "in_reply_to_id": "112844971691041983",
            "in_reply_to_account_id": "109504351558879098",
            "sensitive": false,
            "spoiler_text": "",
            "visibility": "public",
            "language": "en",
            "uri": "https://climatejustice.social/users/jautero/statuses/112846673633779890",
            "url": "https://climatejustice.social/@jautero/112846673633779890",
            "replies_count": 0,
            "reblogs_count": 0,
            "favourites_count": 0,
            "edited_at": null,
            "content": "<p><span class=\"h-card\" translate=\"no\"><a href=\"https://cosocial.ca/@timbray\" class=\"u-url mention\" rel=\"nofollow noopener noreferrer\" target=\"_blank\">@<span>timbray</span></a></span> Do people even realise the irony of wildfires threatening Trans Mountain Pipeline?</p>",
            "reblog": null,
            "account": {
                "id": "106587420346598203",
                "username": "jautero",
                "acct": "jautero@climatejustice.social",
                "display_name": "Juha Autero",
                "locked": false,
                "bot": false,
                "discoverable": true,
                "indexable": false,
                "group": false,
                "created_at": "2021-07-16T00:00:00.000Z",
                "note": "<p>trans rights = human rights</p>",
                "url": "https://climatejustice.social/@jautero",
                "uri": "https://climatejustice.social/users/jautero",
                "avatar": "https://files.mastodon.social/cache/accounts/avatars/106/587/420/346/598/203/original/06e4557b4cee5ee9.png",
                "avatar_static": "https://files.mastodon.social/cache/accounts/avatars/106/587/420/346/598/203/original/06e4557b4cee5ee9.png",
                "header": "https://files.mastodon.social/cache/accounts/headers/106/587/420/346/598/203/original/ec72178ba82fc352.png",
                "header_static": "https://files.mastodon.social/cache/accounts/headers/106/587/420/346/598/203/original/ec72178ba82fc352.png",
                "followers_count": 108,
                "following_count": 365,
                "statuses_count": 240,
                "last_status_at": "2024-08-27",
                "hide_collections": false,
                "emojis": [],
                "fields": []
            },
            "media_attachments": [],
            "mentions": [
                {
                    "id": "109504351558879098",
                    "username": "timbray",
                    "url": "https://cosocial.ca/@timbray",
                    "acct": "timbray@cosocial.ca"
                }
            ],
            "tags": [],
            "emojis": [],
            "card": null,
            "poll": null
        }
    ]
}